Workbook

Sheet Menu
B2: QUALITY AIRCRAFT ACCESSORIES
B3: A Hartzell Engine Technologies Company
B8: QUOTE SYSTEM
B11: SELECT QUOTE TYPE:
B13: 500HR SERVICE | C13: CUSTOMER PROPERTY | D13: EXCHANGE / SALE
B14: 500-hour magneto inspection quotes | C14: Overhaul quotes for customer units | D14: Exchange units & inventory sales
B16: [500HR Button] | C16: [Cust Prop Button] | D16: [Exchange Button]
B20: 5746 E Apache St, Tulsa, OK 74115 | 918-835-6948 | sales@qaainc.com | qaa.com

Sheet 500HR
B1: QUALITY AIRCRAFT ACCESSORIES
B2: 500HR MAGNETO INSPECTION SERVICE QUOTE
B3: A Hartzell Engine Technologies Company
B5: Quote #: | C5: =Config!B2&"-"&TEXT(Config!B3,"00000") | E5: Date: | F5: 01/09/2026
B6: Customer Email: | G6: Approval Req? | H6: No
B9: Magneto P/N | C9: Serial # | D9: Description | E9: 500HR Price | F9: Ovhl Req? | G9: CO Part # | H9: CO Price | I9: Line Total
D10: =IF(B10="","",IFERROR(VLOOKUP(B10&"5H",'Parts Master'!$A:$H,2,FALSE),VLOOKUP(B10,'Parts Master'!$A:$H,2,FALSE))) | E10: =IF(B10="","",IFERROR(VLOOKUP(B10&"5H",'Parts Master'!$A:$H,4,FALSE),Config!$B$5)) | G10: =IF(F10="Yes",SUBSTITUTE(SUBSTITUTE(B10,"5H",""),"-OH","")&"-CO","") | H10: =IF(G10="","",IFERROR(VLOOKUP(G10,'Parts Master'!$A:$H,4,FALSE),0)) | I10: =IF(B10="","",IF(F10="Yes",H10,E10))
D11: =IF(B11="","",IFERROR(VLOOKUP(B11&"5H",'Parts Master'!$A:$H,2,FALSE),VLOOKUP(B11,'Parts Master'!$A:$H,2,FALSE))) | E11: =IF(B11="","",IFERROR(VLOOKUP(B11&"5H",'Parts Master'!$A:$H,4,FALSE),Config!$B$5)) | G11: =IF(F11="Yes",SUBSTITUTE(SUBSTITUTE(B11,"5H",""),"-OH","")&"-CO","") | H11: =IF(G11="","",IFERROR(VLOOKUP(G11,'Parts Master'!$A:$H,4,FALSE),0)) | I11: =IF(B11="","",IF(F11="Yes",H11,E11))
D12: =IF(B12="","",IFERROR(VLOOKUP(B12&"5H",'Parts Master'!$A:$H,2,FALSE),VLOOKUP(B12,'Parts Master'!$A:$H,2,FALSE))) | E12: =IF(B12="","",IFERROR(VLOOKUP(B12&"5H",'Parts Master'!$A:$H,4,FALSE),Config!$B$5)) | G12: =IF(F12="Yes",SUBSTITUTE(SUBSTITUTE(B12,"5H",""),"-OH","")&"-CO","") | H12: =IF(G12="","",IFERROR(VLOOKUP(G12,'Parts Master'!$A:$H,4,FALSE),0)) | I12: =IF(B12="","",IF(F12="Yes",H12,E12))
D13: =IF(B13="","",IFERROR(VLOOKUP(B13&"5H",'Parts Master'!$A:$H,2,FALSE),VLOOKUP(B13,'Parts Master'!$A:$H,2,FALSE))) | E13: =IF(B13="","",IFERROR(VLOOKUP(B13&"5H",'Parts Master'!$A:$H,4,FALSE),Config!$B$5)) | G13: =IF(F13="Yes",SUBSTITUTE(SUBSTITUTE(B13,"5H",""),"-OH","")&"-CO","") | H13: =IF(G13="","",IFERROR(VLOOKUP(G13,'Parts Master'!$A:$H,4,FALSE),0)) | I13: =IF(B13="","",IF(F13="Yes",H13,E13))
D14: =IF(B14="","",IFERROR(VLOOKUP(B14&"5H",'Parts Master'!$A:$H,2,FALSE),VLOOKUP(B14,'Parts Master'!$A:$H,2,FALSE))) | E14: =IF(B14="","",IFERROR(VLOOKUP(B14&"5H",'Parts Master'!$A:$H,4,FALSE),Config!$B$5)) | G14: =IF(F14="Yes",SUBSTITUTE(SUBSTITUTE(B14,"5H",""),"-OH","")&"-CO","") | H14: =IF(G14="","",IFERROR(VLOOKUP(G14,'Parts Master'!$A:$H,4,FALSE),0)) | I14: =IF(B14="","",IF(F14="Yes",H14,E14))
D15: =IF(B15="","",IFERROR(VLOOKUP(B15&"5H",'Parts Master'!$A:$H,2,FALSE),VLOOKUP(B15,'Parts Master'!$A:$H,2,FALSE))) | E15: =IF(B15="","",IFERROR(VLOOKUP(B15&"5H",'Parts Master'!$A:$H,4,FALSE),Config!$B$5)) | G15: =IF(F15="Yes",SUBSTITUTE(SUBSTITUTE(B15,"5H",""),"-OH","")&"-CO","") | H15: =IF(G15="","",IFERROR(VLOOKUP(G15,'Parts Master'!$A:$H,4,FALSE),0)) | I15: =IF(B15="","",IF(F15="Yes",H15,E15))
B17: INSPECTION FINDINGS
B18: Bad Coil | C18: Bad Capacito | D18: Bad Dist Blo | E18: Bad Impulse | F18: Worn Gear | G18: Bad Points | H18: Bad Bearings | I18: Oil in Housi
A19: Unit 1 | B19: ☐ | C19: ☐ | D19: ☐ | E19: ☐ | F19: ☐ | G19: ☐ | H19: ☐ | I19: ☐
A20: Unit 2 | B20: ☐ | C20: ☐ | D20: ☐ | E20: ☐ | F20: ☐ | G20: ☐ | H20: ☐ | I20: ☐
A21: Unit 3 | B21: ☐ | C21: ☐ | D21: ☐ | E21: ☐ | F21: ☐ | G21: ☐ | H21: ☐ | I21: ☐
A22: Unit 4 | B22: ☐ | C22: ☐ | D22: ☐ | E22: ☐ | F22: ☐ | G22: ☐ | H22: ☐ | I22: ☐
A23: Unit 5 | B23: ☐ | C23: ☐ | D23: ☐ | E23: ☐ | F23: ☐ | G23: ☐ | H23: ☐ | I23: ☐
A24: Unit 6 | B24: ☐ | C24: ☐ | D24: ☐ | E24: ☐ | F24: ☐ | G24: ☐ | H24: ☐ | I24: ☐
B26: Units with Findings: | D26: =SUMPRODUCT((COUNTIF(B19:I19,"☑")+COUNTIF(B20:I20,"☑")+COUNTIF(B21:I21,"☑")+COUNTIF(B22:I22,"☑")+COUNTIF(B23:I23,"☑")+COUNTIF(B24:I24,"☑")>0)*1)
B27: Findings Add-On ($110/unit): | D27: =D26*Config!$B$6
G28: 500HR Service Total: | I28: =SUMIF(F10:F15,"<>Yes",E10:E15)
G29: Overhaul Total: | I29: =SUMIF(F10:F15,"Yes",H10:H15)
G30: GRAND TOTAL: | H30: =I28+I29+D27
B32: Notes:
B37: Thank you for choosing Quality Aircraft Accessories!

Sheet Cust Property
B1: QUALITY AIRCRAFT ACCESSORIES
B2: CUSTOMER PROPERTY OVERHAUL QUOTE
B3: A Hartzell Engine Technologies Company
B5: Quote #: | C5: =Config!B2&"-"&TEXT(Config!B3,"00000") | E5: Date: | F5: 01/09/2026 | H5: Updated:
B6: Customer Email: | G6: Tier: | H6: Standard
B7: Approval? | C7: No | D7: Shipping? | E7: No | F7: Payment? | G7: No
B10: Unit P/N (-CO) | C10: Description | D10: Type | E10: Base Labor | F10: Your Price | G10: Exchange Cap
C11: =IF(B11="","",IFERROR(VLOOKUP(B11,'Parts Master'!$A:$H,2,FALSE),"Not Found")) | D11: =IF(B11="","",IF(COUNTIF(BOM!$A:$A,SUBSTITUTE(B11,"-CO",""))>0,"In-House","Vendor")) | F11: =IF(E11="","",E11*(1-VLOOKUP($H$6,Config!$A$10:$B$13,2,FALSE))) | G11: =IF(B11="","",IFERROR(VLOOKUP(SUBSTITUTE(B11,"-CO","-OH"),'Parts Master'!$A:$H,4,FALSE),"N/A"))
C12: =IF(B12="","",IFERROR(VLOOKUP(B12,'Parts Master'!$A:$H,2,FALSE),"Not Found")) | D12: =IF(B12="","",IF(COUNTIF(BOM!$A:$A,SUBSTITUTE(B12,"-CO",""))>0,"In-House","Vendor")) | F12: =IF(E12="","",E12*(1-VLOOKUP($H$6,Config!$A$10:$B$13,2,FALSE))) | G12: =IF(B12="","",IFERROR(VLOOKUP(SUBSTITUTE(B12,"-CO","-OH"),'Parts Master'!$A:$H,4,FALSE),"N/A"))
C13: =IF(B13="","",IFERROR(VLOOKUP(B13,'Parts Master'!$A:$H,2,FALSE),"Not Found")) | D13: =IF(B13="","",IF(COUNTIF(BOM!$A:$A,SUBSTITUTE(B13,"-CO",""))>0,"In-House","Vendor")) | F13: =IF(E13="","",E13*(1-VLOOKUP($H$6,Config!$A$10:$B$13,2,FALSE))) | G13: =IF(B13="","",IFERROR(VLOOKUP(SUBSTITUTE(B13,"-CO","-OH"),'Parts Master'!$A:$H,4,FALSE),"N/A"))
C14: =IF(B14="","",IFERROR(VLOOKUP(B14,'Parts Master'!$A:$H,2,FALSE),"Not Found")) | D14: =IF(B14="","",IF(COUNTIF(BOM!$A:$A,SUBSTITUTE(B14,"-CO",""))>0,"In-House","Vendor")) | F14: =IF(E14="","",E14*(1-VLOOKUP($H$6,Config!$A$10:$B$13,2,FALSE))) | G14: =IF(B14="","",IFERROR(VLOOKUP(SUBSTITUTE(B14,"-CO","-OH"),'Parts Master'!$A:$H,4,FALSE),"N/A"))
B16: OVER & ABOVE PARTS
A17: Unit# | B17: Part # | C17: Description | D17: Qty | E17: Unit Price | F17: Override | G17: Extended | H17: Status
C18: =IF(B18="","",IFERROR(VLOOKUP(B18,'Parts Master'!$A:$H,2,FALSE),"")) | E18: =IF(B18="","",IFERROR(VLOOKUP(B18,'Parts Master'!$A:$H,4,FALSE),0)) | G18: =IF(D18="","",IF(F18<>"",F18*D18,E18*D18))
C19: =IF(B19="","",IFERROR(VLOOKUP(B19,'Parts Master'!$A:$H,2,FALSE),"")) | E19: =IF(B19="","",IFERROR(VLOOKUP(B19,'Parts Master'!$A:$H,4,FALSE),0)) | G19: =IF(D19="","",IF(F19<>"",F19*D19,E19*D19))
C20: =IF(B20="","",IFERROR(VLOOKUP(B20,'Parts Master'!$A:$H,2,FALSE),"")) | E20: =IF(B20="","",IFERROR(VLOOKUP(B20,'Parts Master'!$A:$H,4,FALSE),0)) | G20: =IF(D20="","",IF(F20<>"",F20*D20,E20*D20))
C21: =IF(B21="","",IFERROR(VLOOKUP(B21,'Parts Master'!$A:$H,2,FALSE),"")) | E21: =IF(B21="","",IFERROR(VLOOKUP(B21,'Parts Master'!$A:$H,4,FALSE),0)) | G21: =IF(D21="","",IF(F21<>"",F21*D21,E21*D21))
C22: =IF(B22="","",IFERROR(VLOOKUP(B22,'Parts Master'!$A:$H,2,FALSE),"")) | E22: =IF(B22="","",IFERROR(VLOOKUP(B22,'Parts Master'!$A:$H,4,FALSE),0)) | G22: =IF(D22="","",IF(F22<>"",F22*D22,E22*D22))
C23: =IF(B23="","",IFERROR(VLOOKUP(B23,'Parts Master'!$A:$H,2,FALSE),"")) | E23: =IF(B23="","",IFERROR(VLOOKUP(B23,'Parts Master'!$A:$H,4,FALSE),0)) | G23: =IF(D23="","",IF(F23<>"",F23*D23,E23*D23))
C24: =IF(B24="","",IFERROR(VLOOKUP(B24,'Parts Master'!$A:$H,2,FALSE),"")) | E24: =IF(B24="","",IFERROR(VLOOKUP(B24,'Parts Master'!$A:$H,4,FALSE),0)) | G24: =IF(D24="","",IF(F24<>"",F24*D24,E24*D24))
C25: =IF(B25="","",IFERROR(VLOOKUP(B25,'Parts Master'!$A:$H,2,FALSE),"")) | E25: =IF(B25="","",IFERROR(VLOOKUP(B25,'Parts Master'!$A:$H,4,FALSE),0)) | G25: =IF(D25="","",IF(F25<>"",F25*D25,E25*D25))
C26: =IF(B26="","",IFERROR(VLOOKUP(B26,'Parts Master'!$A:$H,2,FALSE),"")) | E26: =IF(B26="","",IFERROR(VLOOKUP(B26,'Parts Master'!$A:$H,4,FALSE),0)) | G26: =IF(D26="","",IF(F26<>"",F26*D26,E26*D26))
C27: =IF(B27="","",IFERROR(VLOOKUP(B27,'Parts Master'!$A:$H,2,FALSE),"")) | E27: =IF(B27="","",IFERROR(VLOOKUP(B27,'Parts Master'!$A:$H,4,FALSE),0)) | G27: =IF(D27="","",IF(F27<>"",F27*D27,E27*D27))
F29: Labor Total: | G29: =SUM(F11:F14)
F30: Parts Total: | G30: =SUM(G18:G27)
F31: GRAND TOTAL: | G31: =G29+G30
B33: Notes:

Sheet Exchange
A1: QUALITY AIRCRAFT ACCESSORIES
A2: EXCHANGE / INVENTORY SALE QUOTE
A3: A Hartzell Engine Technologies Company
A5: Quote #: | B5: =Config!B2&"-"&TEXT(Config!B3,"00000") | D5: Date: | E5: 01/09/2026
A6: Customer Email: | F6: Tier: | G6: Standard
A7: Approval? | B7: No | C7: Shipping? | D7: No | E7: Payment? | F7: No | G7: Core In Hand? | H7: No
A10: Part # | B10: Description | C10: Cond | D10: Qty | E10: List Price | F10: Your Price | G10: Extended | H10: Core Charge | I10: Stock | J10: Lead Time
B11: =IF(A11="","",IFERROR(VLOOKUP(A11,'Parts Master'!$A:$H,2,FALSE),"Not Found")) | C11: =IF(A11="","",IFERROR(VLOOKUP(A11,'Parts Master'!$A:$H,3,FALSE),"")) | E11: =IF(A11="","",IFERROR(VLOOKUP(A11,'Parts Master'!$A:$H,4,FALSE),0)) | F11: =IF(E11="","",E11*(1-VLOOKUP($G$6,Config!$A$10:$B$13,2,FALSE))) | G11: =IF(D11="","",F11*D11) | H11: =IF(A11="","",IF($H$7="Yes",0,IFERROR(VLOOKUP(A11,'Parts Master'!$A:$H,5,FALSE),0)*D11)) | I11: =IF(A11="","",IFERROR(VLOOKUP(A11,'Parts Master'!$A:$H,6,FALSE),"")) | J11: =IF(A11="","",IFERROR(VLOOKUP(A11,'Parts Master'!$A:$H,7,FALSE),""))
B12: =IF(A12="","",IFERROR(VLOOKUP(A12,'Parts Master'!$A:$H,2,FALSE),"Not Found")) | C12: =IF(A12="","",IFERROR(VLOOKUP(A12,'Parts Master'!$A:$H,3,FALSE),"")) | E12: =IF(A12="","",IFERROR(VLOOKUP(A12,'Parts Master'!$A:$H,4,FALSE),0)) | F12: =IF(E12="","",E12*(1-VLOOKUP($G$6,Config!$A$10:$B$13,2,FALSE))) | G12: =IF(D12="","",F12*D12) | H12: =IF(A12="","",IF($H$7="Yes",0,IFERROR(VLOOKUP(A12,'Parts Master'!$A:$H,5,FALSE),0)*D12)) | I12: =IF(A12="","",IFERROR(VLOOKUP(A12,'Parts Master'!$A:$H,6,FALSE),"")) | J12: =IF(A12="","",IFERROR(VLOOKUP(A12,'Parts Master'!$A:$H,7,FALSE),""))
B13: =IF(A13="","",IFERROR(VLOOKUP(A13,'Parts Master'!$A:$H,2,FALSE),"Not Found")) | C13: =IF(A13="","",IFERROR(VLOOKUP(A13,'Parts Master'!$A:$H,3,FALSE),"")) | E13: =IF(A13="","",IFERROR(VLOOKUP(A13,'Parts Master'!$A:$H,4,FALSE),0)) | F13: =IF(E13="","",E13*(1-VLOOKUP($G$6,Config!$A$10:$B$13,2,FALSE))) | G13: =IF(D13="","",F13*D13) | H13: =IF(A13="","",IF($H$7="Yes",0,IFERROR(VLOOKUP(A13,'Parts Master'!$A:$H,5,FALSE),0)*D13)) | I13: =IF(A13="","",IFERROR(VLOOKUP(A13,'Parts Master'!$A:$H,6,FALSE),"")) | J13: =IF(A13="","",IFERROR(VLOOKUP(A13,'Parts Master'!$A:$H,7,FALSE),""))
B14: =IF(A14="","",IFERROR(VLOOKUP(A14,'Parts Master'!$A:$H,2,FALSE),"Not Found")) | C14: =IF(A14="","",IFERROR(VLOOKUP(A14,'Parts Master'!$A:$H,3,FALSE),"")) | E14: =IF(A14="","",IFERROR(VLOOKUP(A14,'Parts Master'!$A:$H,4,FALSE),0)) | F14: =IF(E14="","",E14*(1-VLOOKUP($G$6,Config!$A$10:$B$13,2,FALSE))) | G14: =IF(D14="","",F14*D14) | H14: =IF(A14="","",IF($H$7="Yes",0,IFERROR(VLOOKUP(A14,'Parts Master'!$A:$H,5,FALSE),0)*D14)) | I14: =IF(A14="","",IFERROR(VLOOKUP(A14,'Parts Master'!$A:$H,6,FALSE),"")) | J14: =IF(A14="","",IFERROR(VLOOKUP(A14,'Parts Master'!$A:$H,7,FALSE),""))
B15: =IF(A15="","",IFERROR(VLOOKUP(A15,'Parts Master'!$A:$H,2,FALSE),"Not Found")) | C15: =IF(A15="","",IFERROR(VLOOKUP(A15,'Parts Master'!$A:$H,3,FALSE),"")) | E15: =IF(A15="","",IFERROR(VLOOKUP(A15,'Parts Master'!$A:$H,4,FALSE),0)) | F15: =IF(E15="","",E15*(1-VLOOKUP($G$6,Config!$A$10:$B$13,2,FALSE))) | G15: =IF(D15="","",F15*D15) | H15: =IF(A15="","",IF($H$7="Yes",0,IFERROR(VLOOKUP(A15,'Parts Master'!$A:$H,5,FALSE),0)*D15)) | I15: =IF(A15="","",IFERROR(VLOOKUP(A15,'Parts Master'!$A:$H,6,FALSE),"")) | J15: =IF(A15="","",IFERROR(VLOOKUP(A15,'Parts Master'!$A:$H,7,FALSE),""))
B16: =IF(A16="","",IFERROR(VLOOKUP(A16,'Parts Master'!$A:$H,2,FALSE),"Not Found")) | C16: =IF(A16="","",IFERROR(VLOOKUP(A16,'Parts Master'!$A:$H,3,FALSE),"")) | E16: =IF(A16="","",IFERROR(VLOOKUP(A16,'Parts Master'!$A:$H,4,FALSE),0)) | F16: =IF(E16="","",E16*(1-VLOOKUP($G$6,Config!$A$10:$B$13,2,FALSE))) | G16: =IF(D16="","",F16*D16) | H16: =IF(A16="","",IF($H$7="Yes",0,IFERROR(VLOOKUP(A16,'Parts Master'!$A:$H,5,FALSE),0)*D16)) | I16: =IF(A16="","",IFERROR(VLOOKUP(A16,'Parts Master'!$A:$H,6,FALSE),"")) | J16: =IF(A16="","",IFERROR(VLOOKUP(A16,'Parts Master'!$A:$H,7,FALSE),""))
B17: =IF(A17="","",IFERROR(VLOOKUP(A17,'Parts Master'!$A:$H,2,FALSE),"Not Found")) | C17: =IF(A17="","",IFERROR(VLOOKUP(A17,'Parts Master'!$A:$H,3,FALSE),"")) | E17: =IF(A17="","",IFERROR(VLOOKUP(A17,'Parts Master'!$A:$H,4,FALSE),0)) | F17: =IF(E17="","",E17*(1-VLOOKUP($G$6,Config!$A$10:$B$13,2,FALSE))) | G17: =IF(D17="","",F17*D17) | H17: =IF(A17="","",IF($H$7="Yes",0,IFERROR(VLOOKUP(A17,'Parts Master'!$A:$H,5,FALSE),0)*D17)) | I17: =IF(A17="","",IFERROR(VLOOKUP(A17,'Parts Master'!$A:$H,6,FALSE),"")) | J17: =IF(A17="","",IFERROR(VLOOKUP(A17,'Parts Master'!$A:$H,7,FALSE),""))
B18: =IF(A18="","",IFERROR(VLOOKUP(A18,'Parts Master'!$A:$H,2,FALSE),"Not Found")) | C18: =IF(A18="","",IFERROR(VLOOKUP(A18,'Parts Master'!$A:$H,3,FALSE),"")) | E18: =IF(A18="","",IFERROR(VLOOKUP(A18,'Parts Master'!$A:$H,4,FALSE),0)) | F18: =IF(E18="","",E18*(1-VLOOKUP($G$6,Config!$A$10:$B$13,2,FALSE))) | G18: =IF(D18="","",F18*D18) | H18: =IF(A18="","",IF($H$7="Yes",0,IFERROR(VLOOKUP(A18,'Parts Master'!$A:$H,5,FALSE),0)*D18)) | I18: =IF(A18="","",IFERROR(VLOOKUP(A18,'Parts Master'!$A:$H,6,FALSE),"")) | J18: =IF(A18="","",IFERROR(VLOOKUP(A18,'Parts Master'!$A:$H,7,FALSE),""))
B19: =IF(A19="","",IFERROR(VLOOKUP(A19,'Parts Master'!$A:$H,2,FALSE),"Not Found")) | C19: =IF(A19="","",IFERROR(VLOOKUP(A19,'Parts Master'!$A:$H,3,FALSE),"")) | E19: =IF(A19="","",IFERROR(VLOOKUP(A19,'Parts Master'!$A:$H,4,FALSE),0)) | F19: =IF(E19="","",E19*(1-VLOOKUP($G$6,Config!$A$10:$B$13,2,FALSE))) | G19: =IF(D19="","",F19*D19) | H19: =IF(A19="","",IF($H$7="Yes",0,IFERROR(VLOOKUP(A19,'Parts Master'!$A:$H,5,FALSE),0)*D19)) | I19: =IF(A19="","",IFERROR(VLOOKUP(A19,'Parts Master'!$A:$H,6,FALSE),"")) | J19: =IF(A19="","",IFERROR(VLOOKUP(A19,'Parts Master'!$A:$H,7,FALSE),""))
B20: =IF(A20="","",IFERROR(VLOOKUP(A20,'Parts Master'!$A:$H,2,FALSE),"Not Found")) | C20: =IF(A20="","",IFERROR(VLOOKUP(A20,'Parts Master'!$A:$H,3,FALSE),"")) | E20: =IF(A20="","",IFERROR(VLOOKUP(A20,'Parts Master'!$A:$H,4,FALSE),0)) | F20: =IF(E20="","",E20*(1-VLOOKUP($G$6,Config!$A$10:$B$13,2,FALSE))) | G20: =IF(D20="","",F20*D20) | H20: =IF(A20="","",IF($H$7="Yes",0,IFERROR(VLOOKUP(A20,'Parts Master'!$A:$H,5,FALSE),0)*D20)) | I20: =IF(A20="","",IFERROR(VLOOKUP(A20,'Parts Master'!$A:$H,6,FALSE),"")) | J20: =IF(A20="","",IFERROR(VLOOKUP(A20,'Parts Master'!$A:$H,7,FALSE),""))
B21: =IF(A21="","",IFERROR(VLOOKUP(A21,'Parts Master'!$A:$H,2,FALSE),"Not Found")) | C21: =IF(A21="","",IFERROR(VLOOKUP(A21,'Parts Master'!$A:$H,3,FALSE),"")) | E21: =IF(A21="","",IFERROR(VLOOKUP(A21,'Parts Master'!$A:$H,4,FALSE),0)) | F21: =IF(E21="","",E21*(1-VLOOKUP($G$6,Config!$A$10:$B$13,2,FALSE))) | G21: =IF(D21="","",F21*D21) | H21: =IF(A21="","",IF($H$7="Yes",0,IFERROR(VLOOKUP(A21,'Parts Master'!$A:$H,5,FALSE),0)*D21)) | I21: =IF(A21="","",IFERROR(VLOOKUP(A21,'Parts Master'!$A:$H,6,FALSE),"")) | J21: =IF(A21="","",IFERROR(VLOOKUP(A21,'Parts Master'!$A:$H,7,FALSE),""))
B22: =IF(A22="","",IFERROR(VLOOKUP(A22,'Parts Master'!$A:$H,2,FALSE),"Not Found")) | C22: =IF(A22="","",IFERROR(VLOOKUP(A22,'Parts Master'!$A:$H,3,FALSE),"")) | E22: =IF(A22="","",IFERROR(VLOOKUP(A22,'Parts Master'!$A:$H,4,FALSE),0)) | F22: =IF(E22="","",E22*(1-VLOOKUP($G$6,Config!$A$10:$B$13,2,FALSE))) | G22: =IF(D22="","",F22*D22) | H22: =IF(A22="","",IF($H$7="Yes",0,IFERROR(VLOOKUP(A22,'Parts Master'!$A:$H,5,FALSE),0)*D22)) | I22: =IF(A22="","",IFERROR(VLOOKUP(A22,'Parts Master'!$A:$H,6,FALSE),"")) | J22: =IF(A22="","",IFERROR(VLOOKUP(A22,'Parts Master'!$A:$H,7,FALSE),""))
A24: Subtotal: | B24: =SUM(G11:G22) | C24: Core Total: | D24: =SUM(H11:H22) | F24: Your Savings: | G24: =SUM(E11:E22)-SUM(F11:F22)
D25: GRAND TOTAL: | E25: =B24+IF(H7="Yes",0,D24)
A27: Notes:

Sheet Parts Master
A1: Part Number | B1: Description | C1: Cond | D1: List Price | E1: Core Charge | F1: Stock | G1: Lead Time | H1: Notes
A2: 10-382320 | B2: S-20/200 Magneto | C2: Base | D2: 0 | E2: 0 | F2: 0 | H2: Base reference
A3: 10-3823205H | B3: S-20/200 Magneto - 500HR Inspection | C3: Svc | D3: 575 | E3: 0 | F3: 0 | G3: 3-5 Days | H3: 500HR service price
A4: 10-382320-CO | B4: S-20/200 Magneto - Customer Overhaul | C4: CO | D4: 895 | E4: 0 | F4: 0 | G4: 7-10 Days | H4: Cust prop overhaul
A5: 10-382320-OH | B5: S-20/200 Magneto - OH Exchange | C5: OH | D5: 2495 | E5: 1000 | F5: 5 | G5: 5-7 Days | H5: Exchange unit
A6: 10-320680 | B6: S-1200 Magneto | C6: Base | D6: 0 | E6: 0 | F6: 0 | H6: Base reference
A7: 10-3206805H | B7: S-1200 Magneto - 500HR Inspection | C7: Svc | D7: 495 | E7: 0 | F7: 0 | G7: 3-5 Days | H7: 500HR service price
A8: 10-320680-CO | B8: S-1200 Magneto - Customer Overhaul | C8: CO | D8: 750 | E8: 0 | F8: 0 | G8: 7-10 Days | H8: Cust prop overhaul
A9: 10-320680-OH | B9: S-1200 Magneto - OH Exchange | C9: OH | D9: 2095 | E9: 800 | F9: 3 | G9: 5-7 Days | H9: Exchange unit
A10: 10-391088 | B10: D-2000/D-3000 Magneto | C10: Base | D10: 0 | E10: 0 | F10: 0 | H10: Base reference
A11: 10-3910885H | B11: D-2000/D-3000 - 500HR Inspection | C11: Svc | D11: 695 | E11: 0 | F11: 0 | G11: 3-5 Days | H11: 500HR service price
A12: 10-391088-CO | B12: D-2000/D-3000 - Customer Overhaul | C12: CO | D12: 1150 | E12: 0 | F12: 0 | G12: 7-10 Days | H12: Cust prop overhaul
A13: 10-391088-OH | B13: D-2000/D-3000 - OH Exchange | C13: OH | D13: 2850 | E13: 1100 | F13: 2 | G13: 5-7 Days | H13: Exchange unit
A14: 10-163020 | B14: Bendix S-20 Magneto | C14: Base | D14: 0 | E14: 0 | F14: 0 | H14: Base reference
A15: 10-1630205H | B15: Bendix S-20 - 500HR Inspection | C15: Svc | D15: 625 | E15: 0 | F15: 0 | G15: 3-5 Days | H15: 500HR service price
A16: 10-163020-CO | B16: Bendix S-20 - Customer Overhaul | C16: CO | D16: 950 | E16: 0 | F16: 0 | G16: 7-10 Days | H16: Cust prop overhaul
A17: 10-163020-OH | B17: Bendix S-20 - OH Exchange | C17: OH | D17: 2650 | E17: 950 | F17: 4 | G17: 5-7 Days | H17: Exchange unit
A18: LW-15473 | B18: Impulse Coupling Assembly | C18: New | D18: 425 | E18: 0 | F18: 12 | G18: In Stock | H18: Common replacement
A19: 10-357170 | B19: Coil Assembly | C19: New | D19: 185 | E19: 0 | F19: 20 | G19: In Stock | H19: Common replacement
A20: 10-357210 | B20: Capacitor | C20: New | D20: 45 | E20: 0 | F20: 50 | G20: In Stock | H20: Common replacement
A21: 10-51360 | B21: Distributor Block | C21: New | D21: 125 | E21: 0 | F21: 15 | G21: In Stock | H21: Common replacement
A22: 10-51350 | B22: Points Assembly | C22: New | D22: 85 | E22: 0 | F22: 30 | G22: In Stock | H22: Common replacement
A23: 10-51340 | B23: Bearing Set | C23: New | D23: 95 | E23: 0 | F23: 25 | G23: In Stock | H23: Common replacement
A24: 10-51330 | B24: Gear Assembly | C24: New | D24: 165 | E24: 0 | F24: 8 | G24: In Stock | H24: Common replacement
A25: 646942-CO | B25: Governor - Customer Overhaul | C25: CO | D25: 1500 | E25: 0 | F25: 0 | G25: 14-21 Days | H25: Vendor overhaul
A26: 646942-OH | B26: Governor - OH Exchange | C26: OH | D26: 3450 | E26: 1500 | F26: 2 | G26: 5-7 Days | H26: Exchange unit
... A28: 478615-OH | B28: Turbocharger - OH Exchange | C28: OH | D28: 5800 | E28: 2500 | F28: 1 | G28: 5-7 Days | H28: Exchange unit

Sheet BOM
A1: Parent P/N | B1: Parent Description | C1: Component P/N | D1: Component Description | E1: Qty Per
A2: 10-382320 | B2: S-20/200 Magneto | C2: 10-357170 | D2: Coil Assembly | E2: 1
A3: 10-382320 | B3: S-20/200 Magneto | C3: 10-357210 | D3: Capacitor | E3: 1
A4: 10-382320 | B4: S-20/200 Magneto | C4: 10-51360 | D4: Distributor Block | E4: 1
A5: 10-382320 | B5: S-20/200 Magneto | C5: LW-15473 | D5: Impulse Coupling | E5: 1
A6: 10-320680 | B6: S-1200 Magneto | C6: 10-357170 | D6: Coil Assembly | E6: 1
A7: 10-320680 | B7: S-1200 Magneto | C7: 10-357210 | D7: Capacitor | E7: 1
A8: 10-391088 | B8: D-2000/D-3000 Magneto | C8: 10-357170 | D8: Coil Assembly | E8: 1
A9: 10-391088 | B9: D-2000/D-3000 Magneto | C9: 10-51360 | D9: Distributor Block | E9: 1

Sheet Config
A1: SYSTEM CONFIGURATION
A2: Quote Prefix | B2: QAA
A3: Next Quote # | B3: 1 | C3: Auto-increments after each email sent
A4: Quote Valid Days | B4: 30
A5: 500HR Default Fee | B5: 550 | C5: Fallback if 5H variant not found
A6: 500HR Findings Add-On | B6: 110 | C6: Flat fee per unit with ANY findings
A9: TIER DISCOUNTS
A10: Standard | B10: 0
A11: Tier 1 | B11: 0.07
A12: Tier 2 | B12: 0.1
A13: Tier 3 | B13: 0.13

Sheet Quote Log
A1: Quote # | B1: Date Sent | C1: Time | D1: Customer Email | E1: Type | F1: Units | G1: Total | H1: Core | I1: Status | J1: Subject | K1: Body Preview

Sheet Email Log
A1: Quote # | B1: Date Sent | C1: Time | D1: Customer Email | E1: Subject | F1: Full Email Body

Sheet Inventory
A1: Part Number | B1: Description | C1: On Hand | D1: Allocated | E1: Available | F1: Location | G1: Last Updated
