Workbook

Sheet Menu
B2: QUALITY AIRCRAFT ACCESSORIES
B3: A Hartzell Engine Technologies Company
B9: QUOTE SYSTEM v13.0
B11: SELECT QUOTE TYPE:
B13: 500HR SERVICE | C13: CUST PROPERTY | D13: EXCHANGE/SALE
B14: Magneto inspection quotes | C14: Customer unit overhauls | D14: Exchange & inventory
B16: [Button] | C16: [Button] | D16: [Button]
B19: QUOTE TRACKER
B20: Track follow-ups, reminders, and quote status
B23: 5746 E Apache St, Tulsa, OK 74115 | 918-835-6948 | sales@qaainc.com

Sheet 500HR
B1: QUALITY AIRCRAFT ACCESSORIES
B2: A Hartzell Engine Technologies Company
B3: 500HR MAGNETO INSPECTION SERVICE QUOTE
B5: Quote #: | C5: =Config!B2&"-"&TEXT(Config!B3,"00000") | F5: Date: | G5: 01/09/2026 | H5: Valid: | I5: 30 Days
B6: Customer Email: | G6: Approval Req? | H6: No
B8: Magneto P/N | C8: Serial # | D8: Description | E8: 500HR Price | F8: Ovhl? | G8: CO Part # | H8: CO Price | I8: Line Total
D9: =IF(B9="","",IFERROR(VLOOKUP(B9&"5H",'Parts Master'!$A:$H,2,FALSE),IFERROR(VLOOKUP(B9,'Parts Master'!$A:$H,2,FALSE),"Not Found"))) | E9: =IF(B9="","",IFERROR(VLOOKUP(B9&"5H",'Parts Master'!$A:$H,4,FALSE),Config!$B$5)) | G9: =IF(F9="Yes",SUBSTITUTE(B9,"5H","")&"-CO","") | H9: =IF(G9="","",IFERROR(VLOOKUP(G9,'Parts Master'!$A:$H,4,FALSE),0)) | I9: =IF(B9="","",IF(F9="Yes",H9,E9))
D10: =IF(B10="","",IFERROR(VLOOKUP(B10&"5H",'Parts Master'!$A:$H,2,FALSE),IFERROR(VLOOKUP(B10,'Parts Master'!$A:$H,2,FALSE),"Not Found"))) | E10: =IF(B10="","",IFERROR(VLOOKUP(B10&"5H",'Parts Master'!$A:$H,4,FALSE),Config!$B$5)) | G10: =IF(F10="Yes",SUBSTITUTE(B10,"5H","")&"-CO","") | H10: =IF(G10="","",IFERROR(VLOOKUP(G10,'Parts Master'!$A:$H,4,FALSE),0)) | I10: =IF(B10="","",IF(F10="Yes",H10,E10))
D11: =IF(B11="","",IFERROR(VLOOKUP(B11&"5H",'Parts Master'!$A:$H,2,FALSE),IFERROR(VLOOKUP(B11,'Parts Master'!$A:$H,2,FALSE),"Not Found"))) | E11: =IF(B11="","",IFERROR(VLOOKUP(B11&"5H",'Parts Master'!$A:$H,4,FALSE),Config!$B$5)) | G11: =IF(F11="Yes",SUBSTITUTE(B11,"5H","")&"-CO","") | H11: =IF(G11="","",IFERROR(VLOOKUP(G11,'Parts Master'!$A:$H,4,FALSE),0)) | I11: =IF(B11="","",IF(F11="Yes",H11,E11))
D12: =IF(B12="","",IFERROR(VLOOKUP(B12&"5H",'Parts Master'!$A:$H,2,FALSE),IFERROR(VLOOKUP(B12,'Parts Master'!$A:$H,2,FALSE),"Not Found"))) | E12: =IF(B12="","",IFERROR(VLOOKUP(B12&"5H",'Parts Master'!$A:$H,4,FALSE),Config!$B$5)) | G12: =IF(F12="Yes",SUBSTITUTE(B12,"5H","")&"-CO","") | H12: =IF(G12="","",IFERROR(VLOOKUP(G12,'Parts Master'!$A:$H,4,FALSE),0)) | I12: =IF(B12="","",IF(F12="Yes",H12,E12))
D13: =IF(B13="","",IFERROR(VLOOKUP(B13&"5H",'Parts Master'!$A:$H,2,FALSE),IFERROR(VLOOKUP(B13,'Parts Master'!$A:$H,2,FALSE),"Not Found"))) | E13: =IF(B13="","",IFERROR(VLOOKUP(B13&"5H",'Parts Master'!$A:$H,4,FALSE),Config!$B$5)) | G13: =IF(F13="Yes",SUBSTITUTE(B13,"5H","")&"-CO","") | H13: =IF(G13="","",IFERROR(VLOOKUP(G13,'Parts Master'!$A:$H,4,FALSE),0)) | I13: =IF(B13="","",IF(F13="Yes",H13,E13))
D14: =IF(B14="","",IFERROR(VLOOKUP(B14&"5H",'Parts Master'!$A:$H,2,FALSE),IFERROR(VLOOKUP(B14,'Parts Master'!$A:$H,2,FALSE),"Not Found"))) | E14: =IF(B14="","",IFERROR(VLOOKUP(B14&"5H",'Parts Master'!$A:$H,4,FALSE),Config!$B$5)) | G14: =IF(F14="Yes",SUBSTITUTE(B14,"5H","")&"-CO","") | H14: =IF(G14="","",IFERROR(VLOOKUP(G14,'Parts Master'!$A:$H,4,FALSE),0)) | I14: =IF(B14="","",IF(F14="Yes",H14,E14))
B16: INSPECTION FINDINGS
B17: Coil | C17: Capacitor | D17: Dist Block | E17: Impulse | F17: Gear | G17: Points | H17: Bearings | I17: Oil ⚠
B18: ☐ | C18: ☐ | D18: ☐ | E18: ☐ | F18: ☐ | G18: ☐ | H18: ☐ | I18: ☐
B19: ☐ | C19: ☐ | D19: ☐ | E19: ☐ | F19: ☐ | G19: ☐ | H19: ☐ | I19: ☐
B20: ☐ | C20: ☐ | D20: ☐ | E20: ☐ | F20: ☐ | G20: ☐ | H20: ☐ | I20: ☐
B21: ☐ | C21: ☐ | D21: ☐ | E21: ☐ | F21: ☐ | G21: ☐ | H21: ☐ | I21: ☐
B22: ☐ | C22: ☐ | D22: ☐ | E22: ☐ | F22: ☐ | G22: ☐ | H22: ☐ | I22: ☐
B23: ☐ | C23: ☐ | D23: ☐ | E23: ☐ | F23: ☐ | G23: ☐ | H23: ☐ | I23: ☐
B25: Findings Add-On: | D25: =SUMPRODUCT((B18:I23<>"☐")*1)/8*Config!$B$6
F27: 500HR Service: | I27: =SUMIF(F9:F14,"<>Yes",E9:E14)
F28: Overhaul Total: | I28: =SUMIF(F9:F14,"Yes",H9:H14)
F29: GRAND TOTAL: | H29: =I27+I28+D25
B31: Notes / Special Instructions:
B35: Thank you for choosing Quality Aircraft Accessories!
B36: 5746 E Apache St, Tulsa, OK 74115 | 918-835-6948 | sales@qaainc.com | qaa.com
B37: Quote valid for 30 days. Prices subject to change. Core charges may apply for exchange units.

Sheet Cust Property
B1: QUALITY AIRCRAFT ACCESSORIES
B2: A Hartzell Engine Technologies Company
B3: CUSTOMER PROPERTY OVERHAUL QUOTE
B5: Quote #: | C5: =Config!B2&"-"&TEXT(Config!B3,"00000") | E5: Date: | F5: 01/09/2026 | G5: Updated:
B6: Customer Email: | F6: Tier: | G6: Standard
B7: Needs: | C7: Approval? | D7: No | E7: Shipping? | F7: No | G7: Payment? | H7: No
B9: Unit P/N | C9: Description | D9: Type | E9: Base Price | F9: Your Price | G9: Exch Cap
C10: =IF(B10="","",IFERROR(VLOOKUP(B10,'Parts Master'!$A:$H,2,FALSE),"Not Found")) | D10: =IF(B10="","",IF(COUNTIF(BOM!$A:$A,SUBSTITUTE(B10,"-CO",""))>0,"In-House","Vendor")) | F10: =IF(E10="","",E10*(1-VLOOKUP($G$6,Config!$A$10:$B$13,2,FALSE))) | G10: =IF(B10="","",IFERROR(VLOOKUP(SUBSTITUTE(B10,"-CO","-OH"),'Parts Master'!$A:$H,4,FALSE),"N/A"))
C11: =IF(B11="","",IFERROR(VLOOKUP(B11,'Parts Master'!$A:$H,2,FALSE),"Not Found")) | D11: =IF(B11="","",IF(COUNTIF(BOM!$A:$A,SUBSTITUTE(B11,"-CO",""))>0,"In-House","Vendor")) | F11: =IF(E11="","",E11*(1-VLOOKUP($G$6,Config!$A$10:$B$13,2,FALSE))) | G11: =IF(B11="","",IFERROR(VLOOKUP(SUBSTITUTE(B11,"-CO","-OH"),'Parts Master'!$A:$H,4,FALSE),"N/A"))
C12: =IF(B12="","",IFERROR(VLOOKUP(B12,'Parts Master'!$A:$H,2,FALSE),"Not Found")) | D12: =IF(B12="","",IF(COUNTIF(BOM!$A:$A,SUBSTITUTE(B12,"-CO",""))>0,"In-House","Vendor")) | F12: =IF(E12="","",E12*(1-VLOOKUP($G$6,Config!$A$10:$B$13,2,FALSE))) | G12: =IF(B12="","",IFERROR(VLOOKUP(SUBSTITUTE(B12,"-CO","-OH"),'Parts Master'!$A:$H,4,FALSE),"N/A"))
C13: =IF(B13="","",IFERROR(VLOOKUP(B13,'Parts Master'!$A:$H,2,FALSE),"Not Found")) | D13: =IF(B13="","",IF(COUNTIF(BOM!$A:$A,SUBSTITUTE(B13,"-CO",""))>0,"In-House","Vendor")) | F13: =IF(E13="","",E13*(1-VLOOKUP($G$6,Config!$A$10:$B$13,2,FALSE))) | G13: =IF(B13="","",IFERROR(VLOOKUP(SUBSTITUTE(B13,"-CO","-OH"),'Parts Master'!$A:$H,4,FALSE),"N/A"))
B15: OVER & ABOVE PARTS
A16: # | B16: Part # | C16: Description | D16: Qty | E16: Unit $ | F16: Override | G16: Extended | H16: Status
C17: =IF(B17="","",IFERROR(VLOOKUP(B17,'Parts Master'!$A:$H,2,FALSE),"")) | E17: =IF(B17="","",IFERROR(VLOOKUP(B17,'Parts Master'!$A:$H,4,FALSE),0)) | G17: =IF(D17="","",IF(F17<>"",F17*D17,E17*D17))
C18: =IF(B18="","",IFERROR(VLOOKUP(B18,'Parts Master'!$A:$H,2,FALSE),"")) | E18: =IF(B18="","",IFERROR(VLOOKUP(B18,'Parts Master'!$A:$H,4,FALSE),0)) | G18: =IF(D18="","",IF(F18<>"",F18*D18,E18*D18))
C19: =IF(B19="","",IFERROR(VLOOKUP(B19,'Parts Master'!$A:$H,2,FALSE),"")) | E19: =IF(B19="","",IFERROR(VLOOKUP(B19,'Parts Master'!$A:$H,4,FALSE),0)) | G19: =IF(D19="","",IF(F19<>"",F19*D19,E19*D19))
C20: =IF(B20="","",IFERROR(VLOOKUP(B20,'Parts Master'!$A:$H,2,FALSE),"")) | E20: =IF(B20="","",IFERROR(VLOOKUP(B20,'Parts Master'!$A:$H,4,FALSE),0)) | G20: =IF(D20="","",IF(F20<>"",F20*D20,E20*D20))
C21: =IF(B21="","",IFERROR(VLOOKUP(B21,'Parts Master'!$A:$H,2,FALSE),"")) | E21: =IF(B21="","",IFERROR(VLOOKUP(B21,'Parts Master'!$A:$H,4,FALSE),0)) | G21: =IF(D21="","",IF(F21<>"",F21*D21,E21*D21))
C22: =IF(B22="","",IFERROR(VLOOKUP(B22,'Parts Master'!$A:$H,2,FALSE),"")) | E22: =IF(B22="","",IFERROR(VLOOKUP(B22,'Parts Master'!$A:$H,4,FALSE),0)) | G22: =IF(D22="","",IF(F22<>"",F22*D22,E22*D22))
C23: =IF(B23="","",IFERROR(VLOOKUP(B23,'Parts Master'!$A:$H,2,FALSE),"")) | E23: =IF(B23="","",IFERROR(VLOOKUP(B23,'Parts Master'!$A:$H,4,FALSE),0)) | G23: =IF(D23="","",IF(F23<>"",F23*D23,E23*D23))
C24: =IF(B24="","",IFERROR(VLOOKUP(B24,'Parts Master'!$A:$H,2,FALSE),"")) | E24: =IF(B24="","",IFERROR(VLOOKUP(B24,'Parts Master'!$A:$H,4,FALSE),0)) | G24: =IF(D24="","",IF(F24<>"",F24*D24,E24*D24))
C25: =IF(B25="","",IFERROR(VLOOKUP(B25,'Parts Master'!$A:$H,2,FALSE),"")) | E25: =IF(B25="","",IFERROR(VLOOKUP(B25,'Parts Master'!$A:$H,4,FALSE),0)) | G25: =IF(D25="","",IF(F25<>"",F25*D25,E25*D25))
C26: =IF(B26="","",IFERROR(VLOOKUP(B26,'Parts Master'!$A:$H,2,FALSE),"")) | E26: =IF(B26="","",IFERROR(VLOOKUP(B26,'Parts Master'!$A:$H,4,FALSE),0)) | G26: =IF(D26="","",IF(F26<>"",F26*D26,E26*D26))
E28: Labor Total: | G28: =SUM(F10:F13)
E29: Parts Total: | G29: =SUM(G17:G26)
E30: GRAND TOTAL: | G30: =G28+G29
B32: Notes:
B36: 5746 E Apache St, Tulsa, OK 74115 | 918-835-6948 | sales@qaainc.com | qaa.com

Sheet Exchange
A1: QUALITY AIRCRAFT ACCESSORIES
A2: A Hartzell Engine Technologies Company
A3: EXCHANGE / INVENTORY SALE QUOTE
A5: Quote #: | B5: =Config!B2&"-"&TEXT(Config!B3,"00000") | D5: Date: | E5: 01/09/2026 | G5: Valid: | H5: 30 Days
A6: Customer Email: | F6: Tier: | G6: Standard
A7: Approval? | B7: No | C7: Ship? | D7: No | E7: Payment? | F7: No | G7: Core In Hand? | H7: No
A9: Part # | B9: Description | C9: Cond | D9: Qty | E9: List $ | F9: Your $ | G9: Extended | H9: Core $ | I9: Stock | J9: Lead
B10: =IF(A10="","",IFERROR(VLOOKUP(A10,'Parts Master'!$A:$H,2,FALSE),"Not Found")) | C10: =IF(A10="","",IFERROR(VLOOKUP(A10,'Parts Master'!$A:$H,3,FALSE),"")) | E10: =IF(A10="","",IFERROR(VLOOKUP(A10,'Parts Master'!$A:$H,4,FALSE),0)) | F10: =IF(E10="","",E10*(1-VLOOKUP($G$6,Config!$A$10:$B$13,2,FALSE))) | G10: =IF(D10="","",F10*D10) | H10: =IF(A10="","",IF($H$7="Yes",0,IFERROR(VLOOKUP(A10,'Parts Master'!$A:$H,5,FALSE),0)*D10)) | I10: =IF(A10="","",IFERROR(VLOOKUP(A10,'Parts Master'!$A:$H,6,FALSE),"")) | J10: =IF(A10="","",IFERROR(VLOOKUP(A10,'Parts Master'!$A:$H,7,FALSE),""))
B11: =IF(A11="","",IFERROR(VLOOKUP(A11,'Parts Master'!$A:$H,2,FALSE),"Not Found")) | C11: =IF(A11="","",IFERROR(VLOOKUP(A11,'Parts Master'!$A:$H,3,FALSE),"")) | E11: =IF(A11="","",IFERROR(VLOOKUP(A11,'Parts Master'!$A:$H,4,FALSE),0)) | F11: =IF(E11="","",E11*(1-VLOOKUP($G$6,Config!$A$10:$B$13,2,FALSE))) | G11: =IF(D11="","",F11*D11) | H11: =IF(A11="","",IF($H$7="Yes",0,IFERROR(VLOOKUP(A11,'Parts Master'!$A:$H,5,FALSE),0)*D11)) | I11: =IF(A11="","",IFERROR(VLOOKUP(A11,'Parts Master'!$A:$H,6,FALSE),"")) | J11: =IF(A11="","",IFERROR(VLOOKUP(A11,'Parts Master'!$A:$H,7,FALSE),""))
B12: =IF(A12="","",IFERROR(VLOOKUP(A12,'Parts Master'!$A:$H,2,FALSE),"Not Found")) | C12: =IF(A12="","",IFERROR(VLOOKUP(A12,'Parts Master'!$A:$H,3,FALSE),"")) | E12: =IF(A12="","",IFERROR(VLOOKUP(A12,'Parts Master'!$A:$H,4,FALSE),0)) | F12: =IF(E12="","",E12*(1-VLOOKUP($G$6,Config!$A$10:$B$13,2,FALSE))) | G12: =IF(D12="","",F12*D12) | H12: =IF(A12="","",IF($H$7="Yes",0,IFERROR(VLOOKUP(A12,'Parts Master'!$A:$H,5,FALSE),0)*D12)) | I12: =IF(A12="","",IFERROR(VLOOKUP(A12,'Parts Master'!$A:$H,6,FALSE),"")) | J12: =IF(A12="","",IFERROR(VLOOKUP(A12,'Parts Master'!$A:$H,7,FALSE),""))
B13: =IF(A13="","",IFERROR(VLOOKUP(A13,'Parts Master'!$A:$H,2,FALSE),"Not Found")) | C13: =IF(A13="","",IFERROR(VLOOKUP(A13,'Parts Master'!$A:$H,3,FALSE),"")) | E13: =IF(A13="","",IFERROR(VLOOKUP(A13,'Parts Master'!$A:$H,4,FALSE),0)) | F13: =IF(E13="","",E13*(1-VLOOKUP($G$6,Config!$A$10:$B$13,2,FALSE))) | G13: =IF(D13="","",F13*D13) | H13: =IF(A13="","",IF($H$7="Yes",0,IFERROR(VLOOKUP(A13,'Parts Master'!$A:$H,5,FALSE),0)*D13)) | I13: =IF(A13="","",IFERROR(VLOOKUP(A13,'Parts Master'!$A:$H,6,FALSE),"")) | J13: =IF(A13="","",IFERROR(VLOOKUP(A13,'Parts Master'!$A:$H,7,FALSE),""))
B14: =IF(A14="","",IFERROR(VLOOKUP(A14,'Parts Master'!$A:$H,2,FALSE),"Not Found")) | C14: =IF(A14="","",IFERROR(VLOOKUP(A14,'Parts Master'!$A:$H,3,FALSE),"")) | E14: =IF(A14="","",IFERROR(VLOOKUP(A14,'Parts Master'!$A:$H,4,FALSE),0)) | F14: =IF(E14="","",E14*(1-VLOOKUP($G$6,Config!$A$10:$B$13,2,FALSE))) | G14: =IF(D14="","",F14*D14) | H14: =IF(A14="","",IF($H$7="Yes",0,IFERROR(VLOOKUP(A14,'Parts Master'!$A:$H,5,FALSE),0)*D14)) | I14: =IF(A14="","",IFERROR(VLOOKUP(A14,'Parts Master'!$A:$H,6,FALSE),"")) | J14: =IF(A14="","",IFERROR(VLOOKUP(A14,'Parts Master'!$A:$H,7,FALSE),""))
B15: =IF(A15="","",IFERROR(VLOOKUP(A15,'Parts Master'!$A:$H,2,FALSE),"Not Found")) | C15: =IF(A15="","",IFERROR(VLOOKUP(A15,'Parts Master'!$A:$H,3,FALSE),"")) | E15: =IF(A15="","",IFERROR(VLOOKUP(A15,'Parts Master'!$A:$H,4,FALSE),0)) | F15: =IF(E15="","",E15*(1-VLOOKUP($G$6,Config!$A$10:$B$13,2,FALSE))) | G15: =IF(D15="","",F15*D15) | H15: =IF(A15="","",IF($H$7="Yes",0,IFERROR(VLOOKUP(A15,'Parts Master'!$A:$H,5,FALSE),0)*D15)) | I15: =IF(A15="","",IFERROR(VLOOKUP(A15,'Parts Master'!$A:$H,6,FALSE),"")) | J15: =IF(A15="","",IFERROR(VLOOKUP(A15,'Parts Master'!$A:$H,7,FALSE),""))
B16: =IF(A16="","",IFERROR(VLOOKUP(A16,'Parts Master'!$A:$H,2,FALSE),"Not Found")) | C16: =IF(A16="","",IFERROR(VLOOKUP(A16,'Parts Master'!$A:$H,3,FALSE),"")) | E16: =IF(A16="","",IFERROR(VLOOKUP(A16,'Parts Master'!$A:$H,4,FALSE),0)) | F16: =IF(E16="","",E16*(1-VLOOKUP($G$6,Config!$A$10:$B$13,2,FALSE))) | G16: =IF(D16="","",F16*D16) | H16: =IF(A16="","",IF($H$7="Yes",0,IFERROR(VLOOKUP(A16,'Parts Master'!$A:$H,5,FALSE),0)*D16)) | I16: =IF(A16="","",IFERROR(VLOOKUP(A16,'Parts Master'!$A:$H,6,FALSE),"")) | J16: =IF(A16="","",IFERROR(VLOOKUP(A16,'Parts Master'!$A:$H,7,FALSE),""))
B17: =IF(A17="","",IFERROR(VLOOKUP(A17,'Parts Master'!$A:$H,2,FALSE),"Not Found")) | C17: =IF(A17="","",IFERROR(VLOOKUP(A17,'Parts Master'!$A:$H,3,FALSE),"")) | E17: =IF(A17="","",IFERROR(VLOOKUP(A17,'Parts Master'!$A:$H,4,FALSE),0)) | F17: =IF(E17="","",E17*(1-VLOOKUP($G$6,Config!$A$10:$B$13,2,FALSE))) | G17: =IF(D17="","",F17*D17) | H17: =IF(A17="","",IF($H$7="Yes",0,IFERROR(VLOOKUP(A17,'Parts Master'!$A:$H,5,FALSE),0)*D17)) | I17: =IF(A17="","",IFERROR(VLOOKUP(A17,'Parts Master'!$A:$H,6,FALSE),"")) | J17: =IF(A17="","",IFERROR(VLOOKUP(A17,'Parts Master'!$A:$H,7,FALSE),""))
B18: =IF(A18="","",IFERROR(VLOOKUP(A18,'Parts Master'!$A:$H,2,FALSE),"Not Found")) | C18: =IF(A18="","",IFERROR(VLOOKUP(A18,'Parts Master'!$A:$H,3,FALSE),"")) | E18: =IF(A18="","",IFERROR(VLOOKUP(A18,'Parts Master'!$A:$H,4,FALSE),0)) | F18: =IF(E18="","",E18*(1-VLOOKUP($G$6,Config!$A$10:$B$13,2,FALSE))) | G18: =IF(D18="","",F18*D18) | H18: =IF(A18="","",IF($H$7="Yes",0,IFERROR(VLOOKUP(A18,'Parts Master'!$A:$H,5,FALSE),0)*D18)) | I18: =IF(A18="","",IFERROR(VLOOKUP(A18,'Parts Master'!$A:$H,6,FALSE),"")) | J18: =IF(A18="","",IFERROR(VLOOKUP(A18,'Parts Master'!$A:$H,7,FALSE),""))
B19: =IF(A19="","",IFERROR(VLOOKUP(A19,'Parts Master'!$A:$H,2,FALSE),"Not Found")) | C19: =IF(A19="","",IFERROR(VLOOKUP(A19,'Parts Master'!$A:$H,3,FALSE),"")) | E19: =IF(A19="","",IFERROR(VLOOKUP(A19,'Parts Master'!$A:$H,4,FALSE),0)) | F19: =IF(E19="","",E19*(1-VLOOKUP($G$6,Config!$A$10:$B$13,2,FALSE))) | G19: =IF(D19="","",F19*D19) | H19: =IF(A19="","",IF($H$7="Yes",0,IFERROR(VLOOKUP(A19,'Parts Master'!$A:$H,5,FALSE),0)*D19)) | I19: =IF(A19="","",IFERROR(VLOOKUP(A19,'Parts Master'!$A:$H,6,FALSE),"")) | J19: =IF(A19="","",IFERROR(VLOOKUP(A19,'Parts Master'!$A:$H,7,FALSE),""))
B20: =IF(A20="","",IFERROR(VLOOKUP(A20,'Parts Master'!$A:$H,2,FALSE),"Not Found")) | C20: =IF(A20="","",IFERROR(VLOOKUP(A20,'Parts Master'!$A:$H,3,FALSE),"")) | E20: =IF(A20="","",IFERROR(VLOOKUP(A20,'Parts Master'!$A:$H,4,FALSE),0)) | F20: =IF(E20="","",E20*(1-VLOOKUP($G$6,Config!$A$10:$B$13,2,FALSE))) | G20: =IF(D20="","",F20*D20) | H20: =IF(A20="","",IF($H$7="Yes",0,IFERROR(VLOOKUP(A20,'Parts Master'!$A:$H,5,FALSE),0)*D20)) | I20: =IF(A20="","",IFERROR(VLOOKUP(A20,'Parts Master'!$A:$H,6,FALSE),"")) | J20: =IF(A20="","",IFERROR(VLOOKUP(A20,'Parts Master'!$A:$H,7,FALSE),""))
B21: =IF(A21="","",IFERROR(VLOOKUP(A21,'Parts Master'!$A:$H,2,FALSE),"Not Found")) | C21: =IF(A21="","",IFERROR(VLOOKUP(A21,'Parts Master'!$A:$H,3,FALSE),"")) | E21: =IF(A21="","",IFERROR(VLOOKUP(A21,'Parts Master'!$A:$H,4,FALSE),0)) | F21: =IF(E21="","",E21*(1-VLOOKUP($G$6,Config!$A$10:$B$13,2,FALSE))) | G21: =IF(D21="","",F21*D21) | H21: =IF(A21="","",IF($H$7="Yes",0,IFERROR(VLOOKUP(A21,'Parts Master'!$A:$H,5,FALSE),0)*D21)) | I21: =IF(A21="","",IFERROR(VLOOKUP(A21,'Parts Master'!$A:$H,6,FALSE),"")) | J21: =IF(A21="","",IFERROR(VLOOKUP(A21,'Parts Master'!$A:$H,7,FALSE),""))
A23: Subtotal: | B23: =SUM(G10:G21) | D23: Core: | E23: =SUM(H10:H21) | F23: =IF(H7="Yes","(WAIVED)","") | G23: Savings: | H23: =SUM(E10:E21)-SUM(F10:F21)
D24: GRAND TOTAL: | F24: =B23+IF(H7="Yes",0,E23)
A26: Notes:
A30: Core charges refunded upon receipt of serviceable core within 30 days.
A31: 5746 E Apache St, Tulsa, OK 74115 | 918-835-6948 | sales@qaainc.com | qaa.com

Sheet Quote Tracker
A1: QUOTE TRACKER - Follow-up & Status Management
A2: ★ RED rows = needs follow-up (7+ days since last contact) | ★ Mark needs as DONE when fulfilled | ★ Set Status to CLOSED when complete
A3: Quote # | B3: Created | C3: Customer Email | D3: Type | E3: Amount | F3: Approval | G3: Shipping | H3: Payment | I3: Reminders | J3: Last Contact | K3: Days Since | L3: Status | M3: Notes / Email Reference
K4: =IF(J4="","",TODAY()-J4)
K5: =IF(J5="","",TODAY()-J5)
K6: =IF(J6="","",TODAY()-J6)
K7: =IF(J7="","",TODAY()-J7)
K8: =IF(J8="","",TODAY()-J8)
K9: =IF(J9="","",TODAY()-J9)
K10: =IF(J10="","",TODAY()-J10)
K11: =IF(J11="","",TODAY()-J11)
K12: =IF(J12="","",TODAY()-J12)
K13: =IF(J13="","",TODAY()-J13)
K14: =IF(J14="","",TODAY()-J14)
K15: =IF(J15="","",TODAY()-J15)
... K53: =IF(J53="","",TODAY()-J53)
A55: SUMMARY
A56: Open Quotes: | B56: =COUNTIF(L4:L53,"OPEN") | C56: Need Follow-up: | D56: =SUMPRODUCT((L4:L53="OPEN")*(K4:K53>=7)) | E56: Closed This Month: | F56: =SUMPRODUCT((L4:L53="CLOSED")*(MONTH(B4:B53)=MONTH(TODAY())))

Sheet Parts Master
A1: Part Number | B1: Description | C1: Cond | D1: List Price | E1: Core Charge | F1: Stock | G1: Lead Time | H1: Notes
A2: 10-382320 | B2: S-20/200 Magneto | C2: Base | D2: 0 | E2: 0 | F2: 0 | H2: Base part
A3: 10-3823205H | B3: S-20/200 Magneto - 500HR Inspection | C3: Svc | D3: 575 | E3: 0 | F3: 0 | G3: 3-5 Days | H3: 500HR price
A4: 10-382320-CO | B4: S-20/200 Magneto - Cust Overhaul | C4: CO | D4: 895 | E4: 0 | F4: 0 | G4: 7-10 Days | H4: Cust prop
A5: 10-382320-OH | B5: S-20/200 Magneto - OH Exchange | C5: OH | D5: 2495 | E5: 1000 | F5: 5 | G5: 5-7 Days | H5: Exchange
A6: 10-320680 | B6: S-1200 Magneto | C6: Base | D6: 0 | E6: 0 | F6: 0 | H6: Base part
A7: 10-3206805H | B7: S-1200 Magneto - 500HR Inspection | C7: Svc | D7: 495 | E7: 0 | F7: 0 | G7: 3-5 Days | H7: 500HR price
A8: 10-320680-CO | B8: S-1200 Magneto - Cust Overhaul | C8: CO | D8: 750 | E8: 0 | F8: 0 | G8: 7-10 Days | H8: Cust prop
A9: 10-320680-OH | B9: S-1200 Magneto - OH Exchange | C9: OH | D9: 2095 | E9: 800 | F9: 3 | G9: 5-7 Days | H9: Exchange
A10: 10-391088 | B10: D-2000/D-3000 Magneto | C10: Base | D10: 0 | E10: 0 | F10: 0 | H10: Base part
A11: 10-3910885H | B11: D-2000/D-3000 - 500HR Inspection | C11: Svc | D11: 695 | E11: 0 | F11: 0 | G11: 3-5 Days | H11: 500HR price
A12: 10-391088-CO | B12: D-2000/D-3000 - Cust Overhaul | C12: CO | D12: 1150 | E12: 0 | F12: 0 | G12: 7-10 Days | H12: Cust prop
A13: 10-391088-OH | B13: D-2000/D-3000 - OH Exchange | C13: OH | D13: 2850 | E13: 1100 | F13: 2 | G13: 5-7 Days | H13: Exchange
A14: 10-163020 | B14: Bendix S-20 Magneto | C14: Base | D14: 0 | E14: 0 | F14: 0 | H14: Base part
A15: 10-1630205H | B15: Bendix S-20 - 500HR Inspection | C15: Svc | D15: 625 | E15: 0 | F15: 0 | G15: 3-5 Days | H15: 500HR price
A16: 10-163020-CO | B16: Bendix S-20 - Cust Overhaul | C16: CO | D16: 950 | E16: 0 | F16: 0 | G16: 7-10 Days | H16: Cust prop
A17: 10-163020-OH | B17: Bendix S-20 - OH Exchange | C17: OH | D17: 2650 | E17: 950 | F17: 4 | G17: 5-7 Days | H17: Exchange
A18: LW-15473 | B18: Impulse Coupling Assembly | C18: New | D18: 425 | E18: 0 | F18: 12 | G18: In Stock
A19: 10-357170 | B19: Coil Assembly | C19: New | D19: 185 | E19: 0 | F19: 20 | G19: In Stock
A20: 10-357210 | B20: Capacitor | C20: New | D20: 45 | E20: 0 | F20: 50 | G20: In Stock
A21: 10-51360 | B21: Distributor Block | C21: New | D21: 125 | E21: 0 | F21: 15 | G21: In Stock
A22: 10-51350 | B22: Points Assembly | C22: New | D22: 85 | E22: 0 | F22: 30 | G22: In Stock
A23: 10-51340 | B23: Bearing Set | C23: New | D23: 95 | E23: 0 | F23: 25 | G23: In Stock
A24: 10-51330 | B24: Gear Assembly | C24: New | D24: 165 | E24: 0 | F24: 8 | G24: In Stock
A25: 646942-CO | B25: Governor - Cust Overhaul | C25: CO | D25: 1500 | E25: 0 | F25: 0 | G25: 14-21 Days | H25: Vendor
A26: 646942-OH | B26: Governor - OH Exchange | C26: OH | D26: 3450 | E26: 1500 | F26: 2 | G26: 5-7 Days
A27: 478615-CO | B27: Turbocharger - Cust Overhaul | C27: CO | D27: 2800 | E27: 0 | F27: 0 | G27: 21-30 Days | H27: Vendor
A28: 478615-OH | B28: Turbocharger - OH Exchange | C28: OH | D28: 5800 | E28: 2500 | F28: 1 | G28: 5-7 Days

Sheet BOM
A1: Parent P/N | B1: Parent Description | C1: Component P/N | D1: Component Desc | E1: Qty
A2: 10-382320 | B2: S-20/200 Magneto | C2: 10-357170 | D2: Coil Assembly | E2: 1
A3: 10-382320 | B3: S-20/200 Magneto | C3: 10-357210 | D3: Capacitor | E3: 1
A4: 10-382320 | B4: S-20/200 Magneto | C4: 10-51360 | D4: Distributor Block | E4: 1
A5: 10-382320 | B5: S-20/200 Magneto | C5: LW-15473 | D5: Impulse Coupling | E5: 1
A6: 10-320680 | B6: S-1200 Magneto | C6: 10-357170 | D6: Coil Assembly | E6: 1
A7: 10-320680 | B7: S-1200 Magneto | C7: 10-357210 | D7: Capacitor | E7: 1
A8: 10-391088 | B8: D-2000/D-3000 | C8: 10-357170 | D8: Coil Assembly | E8: 1

Sheet Config
A1: SYSTEM CONFIGURATION
A2: Quote Prefix | B2: QAA
A3: Next Quote # | B3: 1 | C3: Auto-increments
A4: Quote Valid Days | B4: 30
A5: 500HR Default Fee | B5: 550 | C5: Fallback price
A6: 500HR Findings Fee | B6: 110 | C6: Per unit with findings
A7: Reminder Days | B7: 7 | C7: Days before highlight
A9: TIER DISCOUNTS
A10: Standard | B10: 0
A11: Tier 1 | B11: 0.07
A12: Tier 2 | B12: 0.1
A13: Tier 3 | B13: 0.13
